ConSReg/__init__.py
ConSReg/comb_peak_files.py
ConSReg/coreg.py
ConSReg/edge_list.py
ConSReg/feature_mat.py
ConSReg/imp_score.py
ConSReg/main.py
ConSReg/peak_weight.py
ConSReg/train_test.py
ConSReg/utils.py
ConSReg-1.1.7.dist-info/LICENSE
ConSReg-1.1.7.dist-info/METADATA
ConSReg-1.1.7.dist-info/WHEEL
ConSReg-1.1.7.dist-info/top_level.txt
ConSReg-1.1.7.dist-info/RECORD
