Metadata-Version: 2.1
Name: ConSReg
Version: 1.1.7
Summary: condition-specific regulation
Home-page: https://github.com/LiLabAtVT/ConSReg
Author: Qi Song
Author-email: alexsong@vt.edu
License: MIT
Platform: UNKNOWN
Classifier: Programming Language :: Python :: 3
Classifier: License :: OSI Approved :: MIT License
Classifier: Operating System :: OS Independent
Requires-Python: >=3.6.0
License-File: LICENSE
Requires-Dist: numpy (==1.19)
Requires-Dist: scipy (==1.1.0)
Requires-Dist: pandas (==0.21.1)
Requires-Dist: joblib (>=0.11)
Requires-Dist: rpy2 (==2.8.6)
Requires-Dist: networkx (>=2)
Requires-Dist: scikit-learn (==0.19.1)
Requires-Dist: intervaltree (==2.1.0)
